tests/__init__.py
tests/apps.py
tests/forms.py
tests/root_urls.py
tests/settings.py
tests/tests.py
tests/urls.py
tests/views.py
thumber/__init__.py
thumber/admin.py
thumber/apps.py
thumber/decorators.py
thumber/forms.py
thumber/models.py
thumber/views.py
thumber/migrations/0001_initial.py
thumber/migrations/0002_rename_contentfeedback.py
thumber/migrations/__init__.py
thumber/static/javascript/thumber.js
thumber/templates/thumber/base.html
thumber/templates/thumber/feedback.html
django_thumber-3.0.1.dist-info/LICENSE
django_thumber-3.0.1.dist-info/METADATA
django_thumber-3.0.1.dist-info/WHEEL
django_thumber-3.0.1.dist-info/top_level.txt
django_thumber-3.0.1.dist-info/RECORD
