Metadata-Version: 2.1
Name: django-thumber
Version: 3.0.1
Summary: A Django app to solicit user feedback on various views/pages via a simple widget.
Home-page: https://github.com/uktrade/dit-thumber
Author: David Downes
Author-email: david@downes.co.uk
License: MIT License
Platform: UNKNOWN
Classifier: Environment :: Web Environment
Classifier: Framework :: Django
Classifier: Framework :: Django :: 2.2
Classifier: Framework :: Django :: 3.0
Classifier: Framework :: Django :: 4.0
Classifier: Intended Audience :: Developers
Classifier: License :: OSI Approved :: MIT License
Classifier: Operating System :: OS Independent
Classifier: Programming Language :: Python
Classifier: Programming Language :: Python :: 3.4
Classifier: Programming Language :: Python :: 3.5
Classifier: Programming Language :: Python :: 3.6
Classifier: Topic :: Internet :: WWW/HTTP
Classifier: Topic :: Internet :: WWW/HTTP :: Dynamic Content
Requires-Dist: django (<=4.2,>=1.11)
Provides-Extra: test
Requires-Dist: setuptools (<50.0.0,>=45.2.0) ; extra == 'test'
Requires-Dist: twine (==4.0.2) ; extra == 'test'
Requires-Dist: wheel (<1.0.0,>=0.34.2) ; extra == 'test'
Requires-Dist: black (==20.8b1) ; extra == 'test'
Requires-Dist: blacken-docs (==1.6.0) ; extra == 'test'
Requires-Dist: isort (==5.6.4) ; extra == 'test'
Requires-Dist: flake8 (==3.8.4) ; extra == 'test'
Requires-Dist: pre-commit-hooks (==3.3.0) ; extra == 'test'
Requires-Dist: six (==1.16.0) ; extra == 'test'
